sonix/__init__.py
sonix/boot.py
sonix-0.1.1.dist-info/LICENSE
sonix-0.1.1.dist-info/METADATA
sonix-0.1.1.dist-info/WHEEL
sonix-0.1.1.dist-info/top_level.txt
sonix-0.1.1.dist-info/RECORD
