Metadata-Version: 2.1
Name: sonix
Version: 0.1.1
Summary: Sonix: extract rich analytical signals directly from audio files
Home-page: https://github.com/dimastatz/sonix
Author: Dima Statz
Author-email: dima.statz@gmail.com
License: UNKNOWN
Platform: UNKNOWN
Requires-Python: >=3.8
License-File: LICENSE
Requires-Dist: librosa>=0.10.0
Requires-Dist: soundfile>=0.12.1
Requires-Dist: pytest==7.3.2
Requires-Dist: black==23.3.0
Requires-Dist: pylint==3.2.3
Requires-Dist: pytest-cov==4.1.0
